{
  "Trump": 100,
  "Nike": 46,
  "Donald Trump": 33,
  "Diddy": 33,
  "Taylor Swift": 31,
  "Liam": 29,
  "Kamala Harris": 16,
  "Kardashian": 16,
  "Elon Musk": 15,
  "Biden": 13,
  "Meghan Markle": 12,
  "Golden": 11,
  "Prince Harry": 11,
  "Globes": 11,
  "Ariana Grande": 11,
  "Golden Globes": 9,
  "Jenner": 8,
  "SNL": 7,
  "Selena Gomez": 7,
  "Bieber": 7,
  "Kanye": 7,
  "Jay-Z": 5,
  "Ryan Reynolds": 5,
  "Beyonc\u00e9": 5,
  "Zendaya": 5,
  "Jake Paul": 5,
  "Angelina Jolie": 5,
  "Obama": 4,
  "Tom Holland": 4,
  "Brad Pitt": 3,
  "Tom Brady": 3,
  "Cardi B": 3,
  "Joe Biden": 2,
  "Paris Hilton": 2,
  "Princess of Wales": 2,
  "Drake": 2,
  "Eminem": 2,
  "Sydney Sweeney": 2,
  "Dua Lipa": 2,
  "Lindsay Lohan": 1,
  "Adele": 1,
  "Pete Davidson": 1,
  "Mark Zuckerberg": 1,
  "Harry Styles": 1,
  "Lizzo": 1,
  "LeBron James": 1,
  "Chappell Roan": 1,
  "Jennifer Lawrence": 1,
  "Kendrick Lamar": 1,
  "Saturday Night Live": 1,
  "Olivia Rodrigo": 1,
  "Megan Thee Stallion": 1,
  "50 Cent": 1,
  "Simone Biles": 1,
  "Jon Stewart": 1,
  "Will Ferrell": 0,
  "Andy Cohen": 0,
  "Tim Walz": 0,
  "John Mulaney": 0,
  "MrBeast": 0,
  "Bowen Yang": 0,
  "Austin Butler": 0,
  "Sza": 0,
  "JD Vance": 0,
  "Halsey": 0,
  "Nicki Minaj": 0,
  "Maya Rudolph": 0,
  "Young Thug": 0,
  "Addison Rae": 0,
  "Gabrielle Union": 0,
  "Meek Mill": 0,
  "Jameela Jamil": 0,
  "Lil Yachty": 0,
  "Ali Wong": 0,
  "Tim Cook": 0,
  "Rene\u00e9 Rapp": 0,
  "Bryan Cranston": 0,
  "Lil Wayne": 0,
  "Metro Boomin": 0,
  "Desi Lydic": 0,
  "Livvy Dunne": 0,
  "Ewan McGregor": 0,
  "Bernie Sanders": 0,
  "Kesha": 0,
  "Alison Brie": 0,
  "Tyler The Creator": 0,
  "Big Sean": 0,
  "Larry David": 0,
  "Trent Reznor": 0,
  "Walton Goggins": 0,
  "Tina Fey": 0,
  "Rick Ross": 0,
  "Skylar Grey": 0,
  "Seth Rogan": 0,
  "Sandra Oh": 0,
  "Freddie Gibbs": 0,
  "J.K. Simmons": 0,
  "Eric Andr\u00e9": 0,
  "Giancarlo Esposito": 0,
  "Chloe Bailey": 0,
  "Alchemist": 0,
  "Lil Pump": 0,
  "Adin Ross": 0,
  "Sam Ashgari": 0
}