{
  "Diddy": 100,
  "Nike": 67,
  "Trump": 51,
  "Taylor Swift": 30,
  "Ariana Grande": 26,
  "SNL": 24,
  "Prince Harry": 24,
  "Donald Trump": 20,
  "Kamala Harris": 14,
  "Chappell Roan": 14,
  "Bowen Yang": 10,
  "Saturday Night Live": 8,
  "Maya Rudolph": 8,
  "Cardi B": 8,
  "Bieber": 8,
  "Kardashian": 6,
  "Meghan Markle": 6,
  "Biden": 6,
  "Jenner": 6,
  "Obama": 4,
  "Drake": 4,
  "Kanye": 4,
  "Lil Wayne": 2,
  "Zendaya": 2,
  "Beyonc\u00e9": 2,
  "Brad Pitt": 2,
  "Adele": 2,
  "Kendrick Lamar": 2,
  "Halsey": 2,
  "MrBeast": 2,
  "Paris Hilton": 2,
  "Simone Biles": 2,
  "Princess of Wales": 2,
  "Lindsay Lohan": 2,
  "Addison Rae": 2
}